dataframe_image/__init__.py
dataframe_image/_browser_pdf.py
dataframe_image/_bundler.py
dataframe_image/_command_line.py
dataframe_image/_convert.py
dataframe_image/_latex_pdf.py
dataframe_image/_my_asyncio.py
dataframe_image/_pandas_accessor.py
dataframe_image/_preprocessors.py
dataframe_image/_version.py
dataframe_image/logger.py
dataframe_image/pd_html.py
dataframe_image/converter/__init__.py
dataframe_image/converter/matplotlib_table.py
dataframe_image/converter/browser/__init__.py
dataframe_image/converter/browser/base.py
dataframe_image/converter/browser/chrome_converter.py
dataframe_image/converter/browser/html2image_converter.py
dataframe_image/converter/browser/playwright_converter.py
dataframe_image/converter/browser/selenium_converter.py
dataframe_image/converter/browser/static/download.html
dataframe_image/converter/browser/static/fail.html
dataframe_image/converter/browser/static/form.html
dataframe_image/converter/browser/static/style.css
dataframe_image-0.2.5.data/data/etc/jupyter/nbconfig/notebook.d/dataframe_image.json
tests/__init__.py
tests/conftest.py
tests/dfi-dpi-change-check.xlsx
tests/test_convert.py
tests/test_df_image.py
tests/notebooks/Notebook with DataFrames (default).ipynb
tests/notebooks/Notebook with DataFrames (with dataframe_image).ipynb
tests/notebooks/Short EXECUTED.ipynb
tests/notebooks/Short.ipynb
tests/notebooks/Test 1 EXECUTED.ipynb
tests/notebooks/Test 1.ipynb
tests/notebooks/data/bikes.csv
tests/notebooks/data/covid19.csv
tests/notebooks/media/covid19.gif
tests/notebooks/media/large.png
tests/notebooks/media/ss.png
dataframe_image-0.2.5.dist-info/LICENSE
dataframe_image-0.2.5.dist-info/METADATA
dataframe_image-0.2.5.dist-info/WHEEL
dataframe_image-0.2.5.dist-info/entry_points.txt
dataframe_image-0.2.5.dist-info/top_level.txt
dataframe_image-0.2.5.dist-info/RECORD
