Metadata-Version: 2.1
Name: dataframe_image
Version: 0.2.5
Summary: Embed pandas DataFrames as images in pdf and markdown files when converting from Jupyter Notebooks
Home-page: https://github.com/dexplo/dataframe_image
Author: Ted Petrou
Author-email: petrou.theodore@gmail.com
License: MIT
Keywords: jupyter notebook pandas dataframe image pdf markdown
Classifier: Programming Language :: Python :: 3.8
Classifier: Programming Language :: Python :: 3.9
Classifier: Programming Language :: Python :: 3.10
Classifier: Programming Language :: Python :: 3.11
Classifier: License :: OSI Approved :: MIT License
Classifier: Operating System :: OS Independent
Requires-Python: >=3.8
License-File: LICENSE
Requires-Dist: pandas >=0.24
Requires-Dist: nbconvert >=5
Requires-Dist: aiohttp >=3.10.2
Requires-Dist: requests
Requires-Dist: pillow
Requires-Dist: packaging
Requires-Dist: mistune
Requires-Dist: lxml
Requires-Dist: beautifulsoup4
Requires-Dist: cssutils
Requires-Dist: html2image
Requires-Dist: cssselect
